deepxromm/__init__.py
deepxromm/analyzer.py
deepxromm/autocorrector.py
deepxromm/deepxromm.py
deepxromm/default_config.yaml
deepxromm/network.py
deepxromm/project.py
deepxromm/stylizer.py
deepxromm/xma_data_processor.py
deepxromm/xrommtools.py
deepxromm_fix-0.1.1.dist-info/LICENSE
deepxromm_fix-0.1.1.dist-info/METADATA
deepxromm_fix-0.1.1.dist-info/WHEEL
deepxromm_fix-0.1.1.dist-info/top_level.txt
deepxromm_fix-0.1.1.dist-info/RECORD
