Metadata-Version: 2.1
Name: deepxromm-fix
Version: 0.1.1
Summary: A set of user-friendly tools for DeepLabCut-XMALab marker tracking. Normally under deepxromm, but I as the author do not currently have access
Author-email: Sam DeLap <sjcdelap@gmail.com>
License: MIT License
Project-URL: Homepage, https://github.com/sam-delap/deepxromm
Project-URL: Documentation, https://sam-delap.github.io/deepxromm
Keywords: deepxromm,XMALab,DeepLabCut,XROMM
Classifier: Programming Language :: Python :: 3
Classifier: License :: OSI Approved :: MIT License
Classifier: Operating System :: OS Independent
Requires-Python: >=3.9
License-File: LICENSE
Requires-Dist: blend-modes
Requires-Dist: deeplabcut[tf]
Requires-Dist: imagehash
Provides-Extra: cli
Requires-Dist: ipython ; extra == 'cli'
